out_of_the_box/__init__.py
out_of_the_box/bounding_boxes.py
out_of_the_box/containment_checking.py
out_of_the_box/main.py
out_of_the_box/roi_selector.py
out_of_the_box-1.3.0.dist-info/entry_points.txt
out_of_the_box-1.3.0.dist-info/LICENSE
out_of_the_box-1.3.0.dist-info/METADATA
out_of_the_box-1.3.0.dist-info/WHEEL
out_of_the_box-1.3.0.dist-info/RECORD
