Metadata-Version: 2.1
Name: out-of-the-box
Version: 1.3.0
Summary: "I like to get into boxes."
License: MIT
Author: PypayaTech
Requires-Python: >=3.8,<4.0
Classifier: License :: OSI Approved :: MIT License
Classifier: Programming Language :: Python :: 3
Classifier: Programming Language :: Python :: 3.8
Classifier: Programming Language :: Python :: 3.9
Classifier: Programming Language :: Python :: 3.10
Classifier: Programming Language :: Python :: 3.11
Classifier: Programming Language :: Python :: 3.12
Requires-Dist: numpy (>=1.22.0)
Requires-Dist: opencv-python (>=3.4.0.12,<5.0.0.0)
Requires-Dist: pillow (>=9.0.0,<10.0.0)
